aio_pika/__init__.py
aio_pika/abc.py
aio_pika/channel.py
aio_pika/connection.py
aio_pika/exceptions.py
aio_pika/exchange.py
aio_pika/log.py
aio_pika/message.py
aio_pika/patterns/__init__.py
aio_pika/patterns/base.py
aio_pika/patterns/master.py
aio_pika/patterns/rpc.py
aio_pika/pool.py
aio_pika/py.typed
aio_pika/queue.py
aio_pika/robust_channel.py
aio_pika/robust_connection.py
aio_pika/robust_exchange.py
aio_pika/robust_queue.py
aio_pika/tools.py
aio_pika/transaction.py
aio_pika-9.5.2.dist-info/COPYING
aio_pika-9.5.2.dist-info/METADATA
aio_pika-9.5.2.dist-info/WHEEL
aio_pika-9.5.2.dist-info/RECORD
