Metadata-Version: 2.1
Name: aio-pika
Version: 9.5.2
Summary: Wrapper around the aiormq for asyncio and humans
Home-page: https://github.com/mosquito/aio-pika
License: Apache-2.0
Keywords: rabbitmq,asyncio,amqp,amqp 0.9.1,aiormq
Author: Dmitry Orlov
Author-email: me@mosquito.su
Requires-Python: >=3.8,<4.0
Classifier: Intended Audience :: Developers
Classifier: License :: OSI Approved :: Apache Software License
Classifier: Natural Language :: English
Classifier: Operating System :: MacOS
Classifier: Operating System :: Microsoft
Classifier: Operating System :: POSIX
Classifier: Programming Language :: Python
Classifier: Programming Language :: Python :: 3
Classifier: Programming Language :: Python :: 3.8
Classifier: Programming Language :: Python :: 3.9
Classifier: Programming Language :: Python :: 3.10
Classifier: Programming Language :: Python :: 3.11
Classifier: Programming Language :: Python :: 3.12
Classifier: Programming Language :: Python :: Implementation :: CPython
Classifier: Programming Language :: Python :: Implementation :: PyPy
Classifier: Topic :: Internet
Classifier: Topic :: Software Development
Classifier: Topic :: Software Development :: Libraries
Classifier: Typing :: Typed
Requires-Dist: aiormq (>=6.8.0,<6.9.0)
Requires-Dist: exceptiongroup (>=1,<2)
Requires-Dist: setuptools ; python_version < "3.8"
Requires-Dist: yarl
Project-URL: Documentation, https://docs.aio-pika.com/
Project-URL: Source, https://github.com/mosquito/aio-pika
Project-URL: Tracker, https://github.com/mosquito/aio-pika/issues
